<spellBean>
   <id serialVersionUID="1">
      <guid>94-DE-80-0B-0A-49:d54311bd-e6aa-4fe4-bad4-16aa32a354d1:1368883442416</guid>
   </id>
   <name>Héroïsme suprême </name>
   <school>Enc</school>
   <source>PHB</source>
   <url>http://www.pathfinder-fr.org/Wiki/Pathfinder-RPG.H%c3%a9ro%c3%afsme supr%c3%aame.ashx</url>
   <classesLevel>
      <entry>
         <string>conjurateur</string>
         <integer>5</integer>
      </entry>
      <entry>
         <string>barde</string>
         <integer>5</integer>
      </entry>
      <entry>
         <string>sorcier</string>
         <integer>6</integer>
      </entry>
      <entry>
         <string>magicien</string>
         <integer>6</integer>
      </entry>
   </classesLevel>
</spellBean>