<spellBean>
   <id serialVersionUID="1">
      <guid>94-DE-80-0B-0A-49:0569f3d2-5966-4f3a-8d46-53c0d3828222:1368883444409</guid>
   </id>
   <name>Anticipation du danger </name>
   <school>Div</school>
   <source>UM</source>
   <url>http://www.pathfinder-fr.org/Wiki/Pathfinder-RPG.Anticipation du danger.ashx</url>
   <classesLevel>
      <entry>
         <string>rodeur</string>
         <integer>1</integer>
      </entry>
      <entry>
         <string>barde</string>
         <integer>1</integer>
      </entry>
      <entry>
         <string>magicien</string>
         <integer>1</integer>
      </entry>
      <entry>
         <string>alchimiste</string>
         <integer>1</integer>
      </entry>
   </classesLevel>
</spellBean>