<spellBean>
   <id serialVersionUID="1">
      <guid>94-DE-80-0B-0A-49:8932daf4-41a2-43e0-a681-349594a3a1db:1368883441974</guid>
   </id>
   <name>Détection des pièges </name>
   <school>Div</school>
   <source>PHB</source>
   <url>http://www.pathfinder-fr.org/Wiki/Pathfinder-RPG.D%c3%a9tection des pi%c3%a8ges.ashx</url>
   <classesLevel>
      <entry>
         <string>sorcier</string>
         <integer>2</integer>
      </entry>
      <entry>
         <string>oracle</string>
         <integer>2</integer>
      </entry>
      <entry>
         <string>prêtre</string>
         <integer>2</integer>
      </entry>
      <entry>
         <string>inquisiteur</string>
         <integer>2</integer>
      </entry>
   </classesLevel>
</spellBean>