<spellBean>
   <id serialVersionUID="1">
      <guid>94-DE-80-0B-0A-49:522bc079-a8f3-4372-887f-fc410e74bbd4:1368883443465</guid>
   </id>
   <name>Symbole de douleur </name>
   <school>Nec</school>
   <source>PHB</source>
   <url>http://www.pathfinder-fr.org/Wiki/Pathfinder-RPG.Symbole de douleur.ashx</url>
   <classesLevel>
      <entry>
         <string>sorcier</string>
         <integer>5</integer>
      </entry>
      <entry>
         <string>magicien</string>
         <integer>5</integer>
      </entry>
      <entry>
         <string>oracle</string>
         <integer>5</integer>
      </entry>
      <entry>
         <string>prêtre</string>
         <integer>5</integer>
      </entry>
   </classesLevel>
</spellBean>