<spellBean>
   <id serialVersionUID="1">
      <guid>94-DE-80-0B-0A-49:778af0b9-0037-49ac-83d1-5f0097210eba:1368883443445</guid>
   </id>
   <name>Splendeur de l&apos;aigle de groupe</name>
   <school>Tra</school>
   <source>PHB</source>
   <url>http://www.pathfinder-fr.org/Wiki/Pathfinder-RPG.Splendeur de laigle de groupe.ashx</url>
   <classesLevel>
      <entry>
         <string>barde</string>
         <integer>6</integer>
      </entry>
      <entry>
         <string>magicien</string>
         <integer>6</integer>
      </entry>
      <entry>
         <string>oracle</string>
         <integer>6</integer>
      </entry>
      <entry>
         <string>prêtre</string>
         <integer>6</integer>
      </entry>
   </classesLevel>
</spellBean>