<spellBean>
   <id serialVersionUID="1">
      <guid>94-DE-80-0B-0A-49:2d1176c8-4300-4cfc-8743-54f7b8445c3c:1368883441446</guid>
   </id>
   <name>Cercle de mort </name>
   <school>Nec</school>
   <source>PHB</source>
   <url>http://www.pathfinder-fr.org/Wiki/Pathfinder-RPG.Cercle de mort.ashx</url>
   <classesLevel>
      <entry>
         <string>magicien</string>
         <integer>6</integer>
      </entry>
      <entry>
         <string>inquisiteur</string>
         <integer>6</integer>
      </entry>
   </classesLevel>
</spellBean>