<spellBean>
   <id serialVersionUID="1">
      <guid>94-DE-80-0B-0A-49:8a18c8be-3452-481d-8c5a-757aab65ce6d:1368883441845</guid>
   </id>
   <name>Croissance d&apos;épines </name>
   <school>Tra</school>
   <source>PHB</source>
   <url>http://www.pathfinder-fr.org/Wiki/Pathfinder-RPG.Croissance d%c3%a9pines.ashx</url>
   <classesLevel>
      <entry>
         <string>rodeur</string>
         <integer>2</integer>
      </entry>
      <entry>
         <string>druide</string>
         <integer>3</integer>
      </entry>
   </classesLevel>
</spellBean>