<spellBean>
   <id serialVersionUID="1">
      <guid>94-DE-80-0B-0A-49:641ba060-2434-4c37-b5ce-45eeb5d36b90:1368883443460</guid>
   </id>
   <name>Suggestion de groupe </name>
   <school>Enc</school>
   <source>PHB</source>
   <url>http://www.pathfinder-fr.org/Wiki/Pathfinder-RPG.Suggestion de groupe.ashx</url>
   <classesLevel>
      <entry>
         <string>barde</string>
         <integer>5</integer>
      </entry>
      <entry>
         <string>sorcier</string>
         <integer>6</integer>
      </entry>
      <entry>
         <string>magicien</string>
         <integer>6</integer>
      </entry>
   </classesLevel>
</spellBean>