<spellBean>
   <id serialVersionUID="1">
      <guid>94-DE-80-0B-0A-49:38732229-59dc-4af5-b9d1-16346d5ce0fc:1368883443509</guid>
   </id>
   <name>Ténèbres maudites </name>
   <school>Évo</school>
   <source>PHB</source>
   <url>http://www.pathfinder-fr.org/Wiki/Pathfinder-RPG.T%c3%a9n%c3%a8bres maudites.ashx</url>
   <classesLevel>
      <entry>
         <string>oracle</string>
         <integer>4</integer>
      </entry>
      <entry>
         <string>prêtre</string>
         <integer>4</integer>
      </entry>
      <entry>
         <string>inquisiteur</string>
         <integer>4</integer>
      </entry>
   </classesLevel>
</spellBean>