<spellBean>
   <id serialVersionUID="1">
      <guid>94-DE-80-0B-0A-49:a0daf9a2-1992-4198-a2cc-962aa2af4411:1368883442311</guid>
   </id>
   <name>Frayeur </name>
   <school>Nec</school>
   <source>PHB</source>
   <url>http://www.pathfinder-fr.org/Wiki/Pathfinder-RPG.Frayeur.ashx</url>
   <classesLevel>
      <entry>
         <string>barde</string>
         <integer>1</integer>
      </entry>
      <entry>
         <string>sorcier</string>
         <integer>1</integer>
      </entry>
      <entry>
         <string>magicien</string>
         <integer>1</integer>
      </entry>
      <entry>
         <string>anti paladin</string>
         <integer>1</integer>
      </entry>
      <entry>
         <string>oracle</string>
         <integer>1</integer>
      </entry>
      <entry>
         <string>prêtre</string>
         <integer>1</integer>
      </entry>
      <entry>
         <string>inquisiteur</string>
         <integer>1</integer>
      </entry>
   </classesLevel>
</spellBean>